microgue/__init__.py
microgue/abstract_app.py
microgue/utils.py
microgue/asynchronous/__init__.py
microgue/asynchronous/caches/__init__.py
microgue/asynchronous/caches/abstract_cache.py
microgue/asynchronous/events/__init__.py
microgue/asynchronous/events/abstract_event_bus.py
microgue/asynchronous/queues/__init__.py
microgue/asynchronous/queues/abstract_queue.py
microgue/asynchronous/secrets/__init__.py
microgue/asynchronous/secrets/secrets.py
microgue/asynchronous/services/__init__.py
microgue/asynchronous/services/service.py
microgue/asynchronous/storages/__init__.py
microgue/asynchronous/storages/abstract_storage.py
microgue/caches/__init__.py
microgue/caches/abstract_cache.py
microgue/constants/__init__.py
microgue/constants/error_constants.py
microgue/events/__init__.py
microgue/events/abstract_event_bus.py
microgue/loggers/__init__.py
microgue/loggers/logger.py
microgue/models/__init__.py
microgue/models/abstract_model.py
microgue/models/attributes.py
microgue/models/base_object.py
microgue/models/base_table.py
microgue/models/errors.py
microgue/models/model.py
microgue/models/object.py
microgue/objects/__init__.py
microgue/objects/abstract_expiring_model_object.py
microgue/objects/abstract_model_object.py
microgue/objects/attribute.py
microgue/objects/object.py
microgue/queues/__init__.py
microgue/queues/abstract_queue.py
microgue/secrets/__init__.py
microgue/secrets/secrets.py
microgue/security/__init__.py
microgue/security/generic.py
microgue/services/__init__.py
microgue/services/service.py
microgue/storages/__init__.py
microgue/storages/abstract_storage.py
microgue-4.2.6.dist-info/METADATA
microgue-4.2.6.dist-info/WHEEL
microgue-4.2.6.dist-info/top_level.txt
microgue-4.2.6.dist-info/RECORD
