Metadata-Version: 2.2
Name: microgue
Version: 4.2.6
Summary: This project contains bootstrap code to speed up the development of AWS based microservices
Author: Michael Hudelson
Author-email: michaelhudelson@gmail.com
License: MIT
Requires-Python: >=3.10
Requires-Dist: aioboto3
Requires-Dist: boto3
Requires-Dist: httpx
Requires-Dist: redis
Requires-Dist: requests
Dynamic: author
Dynamic: author-email
Dynamic: description
Dynamic: description-content-type
Dynamic: license
Dynamic: requires-dist
Dynamic: requires-python
Dynamic: summary
